{"moduleName":null,"summaries":[{"symbol":{"__symbol":0,"members":[]},"metadata":{"__symbolic":"class"},"type":{"summaryKind":2,"type":{"reference":{"__symbol":0,"members":[]},"diDeps":[],"lifecycleHooks":[]},"entryComponents":[{"componentType":{"__symbol":1,"members":[]},"componentFactory":{"__symbol":2,"members":[]}},{"componentType":{"__symbol":3,"members":[]},"componentFactory":{"__symbol":4,"members":[]}},{"componentType":{"__symbol":5,"members":[]},"componentFactory":{"__symbol":6,"members":[]}},{"componentType":{"__symbol":7,"members":[]},"componentFactory":{"__symbol":8,"members":[]}},{"componentType":{"__symbol":9,"members":[]},"componentFactory":{"__symbol":10,"members":[]}},{"componentType":{"__symbol":11,"members":[]},"componentFactory":{"__symbol":12,"members":[]}},{"componentType":{"__symbol":13,"members":[]},"componentFactory":{"__symbol":14,"members":[]}},{"componentType":{"__symbol":15,"members":[]},"componentFactory":{"__symbol":16,"members":[]}},{"componentType":{"__symbol":17,"members":[]},"componentFactory":{"__symbol":18,"members":[]}},{"componentType":{"__symbol":19,"members":[]},"componentFactory":{"__symbol":20,"members":[]}},{"componentType":{"__symbol":21,"members":[]},"componentFactory":{"__symbol":22,"members":[]}},{"componentType":{"__symbol":23,"members":[]},"componentFactory":{"__symbol":24,"members":[]}},{"componentType":{"__symbol":25,"members":[]},"componentFactory":{"__symbol":26,"members":[]}},{"componentType":{"__symbol":27,"members":[]},"componentFactory":{"__symbol":28,"members":[]}},{"componentType":{"__symbol":29,"members":[]},"componentFactory":{"__symbol":30,"members":[]}},{"componentType":{"__symbol":31,"members":[]},"componentFactory":{"__symbol":32,"members":[]}},{"componentType":{"__symbol":33,"members":[]},"componentFactory":{"__symbol":34,"members":[]}},{"componentType":{"__symbol":35,"members":[]},"componentFactory":{"__symbol":36,"members":[]}}],"providers":[{"provider":{"token":{"identifier":{"reference":{"__symbol":37,"members":[]}}},"useClass":{"reference":{"__symbol":38,"members":[]},"diDeps":[{"isAttribute":false,"isHost":false,"isSelf":false,"isSkipSelf":false,"isOptional":false,"token":{"identifier":{"reference":{"__symbol":39,"members":[]}}}},{"isAttribute":false,"isHost":false,"isSelf":false,"isSkipSelf":false,"isOptional":true,"token":{"identifier":{"reference":{"__symbol":40,"members":[]}}}}],"lifecycleHooks":[]},"useFactory":null,"deps":[{"isAttribute":false,"isHost":false,"isSelf":false,"isSkipSelf":false,"isOptional":false,"token":{"identifier":{"reference":{"__symbol":39,"members":[]}}}},{"isAttribute":false,"isHost":false,"isSelf":false,"isSkipSelf":false,"isOptional":true,"token":{"identifier":{"reference":{"__symbol":40,"members":[]}}}}],"multi":false},"module":{"reference":{"__symbol":41,"members":[]},"diDeps":[],"lifecycleHooks":[]}},{"provider":{"token":{"identifier":{"reference":{"__symbol":42,"members":[]},"diDeps":[{"isAttribute":false,"isHost":false,"isSelf":false,"isSkipSelf":false,"isOptional":false,"token":{"identifier":{"reference":{"__symbol":43,"members":[]}}}},{"isAttribute":false,"isHost":false,"isSelf":false,"isSkipSelf":false,"isOptional":false,"token":{"identifier":{"reference":{"__symbol":44,"members":[]}}}}],"lifecycleHooks":[]}},"useClass":{"reference":{"__symbol":42,"members":[]},"diDeps":[{"isAttribute":false,"isHost":false,"isSelf":false,"isSkipSelf":false,"isOptional":false,"token":{"identifier":{"reference":{"__symbol":43,"members":[]}}}},{"isAttribute":false,"isHost":false,"isSelf":false,"isSkipSelf":false,"isOptional":false,"token":{"identifier":{"reference":{"__symbol":44,"members":[]}}}}],"lifecycleHooks":[]},"useFactory":null,"deps":[{"isAttribute":false,"isHost":false,"isSelf":false,"isSkipSelf":false,"isOptional":false,"token":{"identifier":{"reference":{"__symbol":43,"members":[]}}}},{"isAttribute":false,"isHost":false,"isSelf":false,"isSkipSelf":false,"isOptional":false,"token":{"identifier":{"reference":{"__symbol":44,"members":[]}}}}],"multi":false},"module":{"reference":{"__symbol":45,"members":[]},"diDeps":[],"lifecycleHooks":[]}},{"provider":{"token":{"identifier":{"reference":{"__symbol":46,"members":[]}}},"useClass":null,"useFactory":null,"useExisting":{"identifier":{"reference":{"__symbol":42,"members":[]}}},"multi":true},"module":{"reference":{"__symbol":45,"members":[]},"diDeps":[],"lifecycleHooks":[]}},{"provider":{"token":{"identifier":{"reference":{"__symbol":43,"members":[]}}},"useClass":{"reference":{"__symbol":47,"members":[]},"diDeps":[{"isAttribute":false,"isHost":false,"isSelf":false,"isSkipSelf":false,"isOptional":false,"token":{"identifier":{"reference":{"__symbol":48,"members":[]}}}},{"isAttribute":false,"isHost":false,"isSelf":false,"isSkipSelf":false,"isOptional":false,"token":{"identifier":{"reference":{"__symbol":49,"members":[]}}}},{"isAttribute":false,"isHost":false,"isSelf":false,"isSkipSelf":false,"isOptional":false,"token":{"identifier":{"reference":{"__symbol":50,"members":[]}}}}],"lifecycleHooks":[]},"useFactory":null,"deps":[{"isAttribute":false,"isHost":false,"isSelf":false,"isSkipSelf":false,"isOptional":false,"token":{"identifier":{"reference":{"__symbol":48,"members":[]}}}},{"isAttribute":false,"isHost":false,"isSelf":false,"isSkipSelf":false,"isOptional":false,"token":{"identifier":{"reference":{"__symbol":49,"members":[]}}}},{"isAttribute":false,"isHost":false,"isSelf":false,"isSkipSelf":false,"isOptional":false,"token":{"identifier":{"reference":{"__symbol":50,"members":[]}}}}],"multi":false},"module":{"reference":{"__symbol":45,"members":[]},"diDeps":[],"lifecycleHooks":[]}},{"provider":{"token":{"identifier":{"reference":{"__symbol":50,"members":[]}}},"useClass":null,"useValue":"XSRF-TOKEN","useFactory":null,"multi":false},"module":{"reference":{"__symbol":45,"members":[]},"diDeps":[],"lifecycleHooks":[]}},{"provider":{"token":{"identifier":{"reference":{"__symbol":44,"members":[]}}},"useClass":null,"useValue":"X-XSRF-TOKEN","useFactory":null,"multi":false},"module":{"reference":{"__symbol":45,"members":[]},"diDeps":[],"lifecycleHooks":[]}},{"provider":{"token":{"identifier":{"reference":{"__symbol":50,"members":[]}}},"useClass":null,"useValue":"XSRF-TOKEN","useFactory":null,"multi":false},"module":{"reference":{"__symbol":51,"members":[]},"diDeps":[],"lifecycleHooks":[]}},{"provider":{"token":{"identifier":{"reference":{"__symbol":44,"members":[]}}},"useClass":null,"useValue":"X-XSRF-TOKEN","useFactory":null,"multi":false},"module":{"reference":{"__symbol":51,"members":[]},"diDeps":[],"lifecycleHooks":[]}},{"provider":{"token":{"identifier":{"reference":{"__symbol":52,"members":[]},"diDeps":[{"isAttribute":false,"isHost":false,"isSelf":false,"isSkipSelf":false,"isOptional":false,"token":{"identifier":{"reference":{"__symbol":53,"members":[]}}}}],"lifecycleHooks":[]}},"useClass":{"reference":{"__symbol":52,"members":[]},"diDeps":[{"isAttribute":false,"isHost":false,"isSelf":false,"isSkipSelf":false,"isOptional":false,"token":{"identifier":{"reference":{"__symbol":53,"members":[]}}}}],"lifecycleHooks":[]},"useFactory":null,"deps":[{"isAttribute":false,"isHost":false,"isSelf":false,"isSkipSelf":false,"isOptional":false,"token":{"identifier":{"reference":{"__symbol":53,"members":[]}}}}],"multi":false},"module":{"reference":{"__symbol":51,"members":[]},"diDeps":[],"lifecycleHooks":[]}},{"provider":{"token":{"identifier":{"reference":{"__symbol":53,"members":[]}}},"useClass":{"reference":{"__symbol":54,"members":[]},"diDeps":[{"isAttribute":false,"isHost":false,"isSelf":false,"isSkipSelf":false,"isOptional":false,"token":{"identifier":{"reference":{"__symbol":55,"members":[]}}}},{"isAttribute":false,"isHost":false,"isSelf":false,"isSkipSelf":false,"isOptional":false,"token":{"identifier":{"reference":{"__symbol":56,"members":[]}}}}],"lifecycleHooks":[]},"useFactory":null,"deps":[{"isAttribute":false,"isHost":false,"isSelf":false,"isSkipSelf":false,"isOptional":false,"token":{"identifier":{"reference":{"__symbol":55,"members":[]}}}},{"isAttribute":false,"isHost":false,"isSelf":false,"isSkipSelf":false,"isOptional":false,"token":{"identifier":{"reference":{"__symbol":56,"members":[]}}}}],"multi":false},"module":{"reference":{"__symbol":51,"members":[]},"diDeps":[],"lifecycleHooks":[]}},{"provider":{"token":{"identifier":{"reference":{"__symbol":57,"members":[]},"diDeps":[{"isAttribute":false,"isHost":false,"isSelf":false,"isSkipSelf":false,"isOptional":false,"token":{"identifier":{"reference":{"__symbol":58,"members":[]}}}}],"lifecycleHooks":[]}},"useClass":{"reference":{"__symbol":57,"members":[]},"diDeps":[{"isAttribute":false,"isHost":false,"isSelf":false,"isSkipSelf":false,"isOptional":false,"token":{"identifier":{"reference":{"__symbol":58,"members":[]}}}}],"lifecycleHooks":[]},"useFactory":null,"deps":[{"isAttribute":false,"isHost":false,"isSelf":false,"isSkipSelf":false,"isOptional":false,"token":{"identifier":{"reference":{"__symbol":58,"members":[]}}}}],"multi":false},"module":{"reference":{"__symbol":51,"members":[]},"diDeps":[],"lifecycleHooks":[]}},{"provider":{"token":{"identifier":{"reference":{"__symbol":55,"members":[]}}},"useClass":null,"useFactory":null,"useExisting":{"identifier":{"reference":{"__symbol":57,"members":[]}}},"multi":false},"module":{"reference":{"__symbol":51,"members":[]},"diDeps":[],"lifecycleHooks":[]}},{"provider":{"token":{"identifier":{"reference":{"__symbol":59,"members":[]},"diDeps":[],"lifecycleHooks":[]}},"useClass":{"reference":{"__symbol":59,"members":[]},"diDeps":[],"lifecycleHooks":[]},"useFactory":null,"deps":[],"multi":false},"module":{"reference":{"__symbol":51,"members":[]},"diDeps":[],"lifecycleHooks":[]}},{"provider":{"token":{"identifier":{"reference":{"__symbol":58,"members":[]}}},"useClass":null,"useFactory":null,"useExisting":{"identifier":{"reference":{"__symbol":59,"members":[]}}},"multi":false},"module":{"reference":{"__symbol":51,"members":[]},"diDeps":[],"lifecycleHooks":[]}},{"provider":{"token":{"identifier":{"reference":{"__symbol":60,"members":[]},"diDeps":[],"lifecycleHooks":[]}},"useClass":{"reference":{"__symbol":60,"members":[]},"diDeps":[],"lifecycleHooks":[]},"useFactory":null,"deps":[],"multi":false},"module":{"reference":{"__symbol":61,"members":[]},"diDeps":[],"lifecycleHooks":[]}},{"provider":{"token":{"identifier":{"reference":{"__symbol":62,"members":[]},"diDeps":[],"lifecycleHooks":[]}},"useClass":{"reference":{"__symbol":62,"members":[]},"diDeps":[],"lifecycleHooks":[]},"useFactory":null,"deps":[],"multi":false},"module":{"reference":{"__symbol":63,"members":[]},"diDeps":[],"lifecycleHooks":[]}},{"provider":{"token":{"identifier":{"reference":{"__symbol":60,"members":[]},"diDeps":[],"lifecycleHooks":[]}},"useClass":{"reference":{"__symbol":60,"members":[]},"diDeps":[],"lifecycleHooks":[]},"useFactory":null,"deps":[],"multi":false},"module":{"reference":{"__symbol":63,"members":[]},"diDeps":[],"lifecycleHooks":[]}},{"provider":{"token":{"identifier":{"reference":{"__symbol":64,"members":[]},"diDeps":[{"isAttribute":false,"isHost":false,"isSelf":false,"isSkipSelf":false,"isOptional":false,"token":{"identifier":{"reference":{"__symbol":65,"members":[]}}}},{"isAttribute":false,"isHost":false,"isSelf":false,"isSkipSelf":false,"isOptional":false,"token":{"identifier":{"reference":{"__symbol":66,"members":[]}}}},{"isAttribute":false,"isHost":false,"isSelf":false,"isSkipSelf":false,"isOptional":false,"token":{"identifier":{"reference":{"__symbol":67,"members":[]}}}},{"isAttribute":false,"isHost":false,"isSelf":false,"isSkipSelf":false,"isOptional":false,"token":{"identifier":{"reference":{"__symbol":68,"members":[]}}}},{"isAttribute":false,"isHost":false,"isSelf":false,"isSkipSelf":false,"isOptional":false,"token":{"identifier":{"reference":{"__symbol":69,"members":[]}}}},{"isAttribute":false,"isHost":false,"isSelf":false,"isSkipSelf":false,"isOptional":false,"token":{"identifier":{"reference":{"__symbol":56,"members":[]}}}},{"isAttribute":false,"isHost":false,"isSelf":false,"isSkipSelf":false,"isOptional":false,"token":{"identifier":{"reference":{"__symbol":70,"members":[]}}}},{"isAttribute":false,"isHost":false,"isSelf":false,"isSkipSelf":false,"isOptional":false,"token":{"identifier":{"reference":{"__symbol":48,"members":[]}}}},{"isAttribute":false,"isHost":false,"isSelf":false,"isSkipSelf":false,"isOptional":false,"token":{"identifier":{"reference":{"__symbol":71,"members":[]}}}},{"isAttribute":false,"isHost":false,"isSelf":false,"isSkipSelf":false,"isOptional":true,"token":{"identifier":{"reference":{"__symbol":72,"members":[]}}}}],"lifecycleHooks":[]}},"useClass":{"reference":{"__symbol":64,"members":[]},"diDeps":[{"isAttribute":false,"isHost":false,"isSelf":false,"isSkipSelf":false,"isOptional":false,"token":{"identifier":{"reference":{"__symbol":65,"members":[]}}}},{"isAttribute":false,"isHost":false,"isSelf":false,"isSkipSelf":false,"isOptional":false,"token":{"identifier":{"reference":{"__symbol":66,"members":[]}}}},{"isAttribute":false,"isHost":false,"isSelf":false,"isSkipSelf":false,"isOptional":false,"token":{"identifier":{"reference":{"__symbol":67,"members":[]}}}},{"isAttribute":false,"isHost":false,"isSelf":false,"isSkipSelf":false,"isOptional":false,"token":{"identifier":{"reference":{"__symbol":68,"members":[]}}}},{"isAttribute":false,"isHost":false,"isSelf":false,"isSkipSelf":false,"isOptional":false,"token":{"identifier":{"reference":{"__symbol":69,"members":[]}}}},{"isAttribute":false,"isHost":false,"isSelf":false,"isSkipSelf":false,"isOptional":false,"token":{"identifier":{"reference":{"__symbol":56,"members":[]}}}},{"isAttribute":false,"isHost":false,"isSelf":false,"isSkipSelf":false,"isOptional":false,"token":{"identifier":{"reference":{"__symbol":70,"members":[]}}}},{"isAttribute":false,"isHost":false,"isSelf":false,"isSkipSelf":false,"isOptional":false,"token":{"identifier":{"reference":{"__symbol":48,"members":[]}}}},{"isAttribute":false,"isHost":false,"isSelf":false,"isSkipSelf":false,"isOptional":false,"token":{"identifier":{"reference":{"__symbol":71,"members":[]}}}},{"isAttribute":false,"isHost":false,"isSelf":false,"isSkipSelf":false,"isOptional":true,"token":{"identifier":{"reference":{"__symbol":72,"members":[]}}}}],"lifecycleHooks":[]},"useFactory":null,"deps":[{"isAttribute":false,"isHost":false,"isSelf":false,"isSkipSelf":false,"isOptional":false,"token":{"identifier":{"reference":{"__symbol":65,"members":[]}}}},{"isAttribute":false,"isHost":false,"isSelf":false,"isSkipSelf":false,"isOptional":false,"token":{"identifier":{"reference":{"__symbol":66,"members":[]}}}},{"isAttribute":false,"isHost":false,"isSelf":false,"isSkipSelf":false,"isOptional":false,"token":{"identifier":{"reference":{"__symbol":67,"members":[]}}}},{"isAttribute":false,"isHost":false,"isSelf":false,"isSkipSelf":false,"isOptional":false,"token":{"identifier":{"reference":{"__symbol":68,"members":[]}}}},{"isAttribute":false,"isHost":false,"isSelf":false,"isSkipSelf":false,"isOptional":false,"token":{"identifier":{"reference":{"__symbol":69,"members":[]}}}},{"isAttribute":false,"isHost":false,"isSelf":false,"isSkipSelf":false,"isOptional":false,"token":{"identifier":{"reference":{"__symbol":56,"members":[]}}}},{"isAttribute":false,"isHost":false,"isSelf":false,"isSkipSelf":false,"isOptional":false,"token":{"identifier":{"reference":{"__symbol":70,"members":[]}}}},{"isAttribute":false,"isHost":false,"isSelf":false,"isSkipSelf":false,"isOptional":false,"token":{"identifier":{"reference":{"__symbol":48,"members":[]}}}},{"isAttribute":false,"isHost":false,"isSelf":false,"isSkipSelf":false,"isOptional":false,"token":{"identifier":{"reference":{"__symbol":71,"members":[]}}}},{"isAttribute":false,"isHost":false,"isSelf":false,"isSkipSelf":false,"isOptional":true,"token":{"identifier":{"reference":{"__symbol":72,"members":[]}}}}],"multi":false},"module":{"reference":{"__symbol":73,"members":[]},"diDeps":[],"lifecycleHooks":[]}},{"provider":{"token":{"identifier":{"reference":{"__symbol":74,"members":[]}}},"useClass":null,"useFactory":{"reference":{"__symbol":75,"members":[]},"diDeps":[{"isAttribute":false,"isHost":false,"isSelf":false,"isSkipSelf":false,"isOptional":false,"token":{"identifier":{"reference":{"__symbol":64,"members":[]}}}}]},"deps":[{"isAttribute":false,"isHost":false,"isSelf":false,"isSkipSelf":false,"isOptional":false,"token":{"identifier":{"reference":{"__symbol":64,"members":[]}}}}],"multi":false},"module":{"reference":{"__symbol":73,"members":[]},"diDeps":[],"lifecycleHooks":[]}},{"provider":{"token":{"identifier":{"reference":{"__symbol":76,"members":[]},"diDeps":[{"isAttribute":false,"isHost":false,"isSelf":false,"isSkipSelf":false,"isOptional":false,"token":{"identifier":{"reference":{"__symbol":64,"members":[]}}}},{"isAttribute":false,"isHost":false,"isSelf":false,"isSkipSelf":false,"isOptional":false,"token":{"identifier":{"reference":{"__symbol":56,"members":[]}}}},{"isAttribute":false,"isHost":false,"isSelf":false,"isSkipSelf":false,"isOptional":true,"token":{"identifier":{"reference":{"__symbol":72,"members":[]}}}},{"isAttribute":false,"isHost":false,"isSelf":false,"isSkipSelf":false,"isOptional":true,"token":{"identifier":{"reference":{"__symbol":77,"members":[]}}}},{"isAttribute":false,"isHost":false,"isSelf":false,"isSkipSelf":false,"isOptional":false,"token":{"identifier":{"reference":{"__symbol":78,"members":[]}}}},{"isAttribute":false,"isHost":false,"isSelf":false,"isSkipSelf":true,"isOptional":true,"token":{"identifier":{"reference":{"__symbol":76,"members":[]}}}},{"isAttribute":false,"isHost":false,"isSelf":false,"isSkipSelf":false,"isOptional":false,"token":{"identifier":{"reference":{"__symbol":66,"members":[]}}}}],"lifecycleHooks":[1]}},"useClass":{"reference":{"__symbol":76,"members":[]},"diDeps":[{"isAttribute":false,"isHost":false,"isSelf":false,"isSkipSelf":false,"isOptional":false,"token":{"identifier":{"reference":{"__symbol":64,"members":[]}}}},{"isAttribute":false,"isHost":false,"isSelf":false,"isSkipSelf":false,"isOptional":false,"token":{"identifier":{"reference":{"__symbol":56,"members":[]}}}},{"isAttribute":false,"isHost":false,"isSelf":false,"isSkipSelf":false,"isOptional":true,"token":{"identifier":{"reference":{"__symbol":72,"members":[]}}}},{"isAttribute":false,"isHost":false,"isSelf":false,"isSkipSelf":false,"isOptional":true,"token":{"identifier":{"reference":{"__symbol":77,"members":[]}}}},{"isAttribute":false,"isHost":false,"isSelf":false,"isSkipSelf":false,"isOptional":false,"token":{"identifier":{"reference":{"__symbol":78,"members":[]}}}},{"isAttribute":false,"isHost":false,"isSelf":false,"isSkipSelf":true,"isOptional":true,"token":{"identifier":{"reference":{"__symbol":76,"members":[]}}}},{"isAttribute":false,"isHost":false,"isSelf":false,"isSkipSelf":false,"isOptional":false,"token":{"identifier":{"reference":{"__symbol":66,"members":[]}}}}],"lifecycleHooks":[1]},"useFactory":null,"deps":[{"isAttribute":false,"isHost":false,"isSelf":false,"isSkipSelf":false,"isOptional":false,"token":{"identifier":{"reference":{"__symbol":64,"members":[]}}}},{"isAttribute":false,"isHost":false,"isSelf":false,"isSkipSelf":false,"isOptional":false,"token":{"identifier":{"reference":{"__symbol":56,"members":[]}}}},{"isAttribute":false,"isHost":false,"isSelf":false,"isSkipSelf":false,"isOptional":true,"token":{"identifier":{"reference":{"__symbol":72,"members":[]}}}},{"isAttribute":false,"isHost":false,"isSelf":false,"isSkipSelf":false,"isOptional":true,"token":{"identifier":{"reference":{"__symbol":77,"members":[]}}}},{"isAttribute":false,"isHost":false,"isSelf":false,"isSkipSelf":false,"isOptional":false,"token":{"identifier":{"reference":{"__symbol":78,"members":[]}}}},{"isAttribute":false,"isHost":false,"isSelf":false,"isSkipSelf":true,"isOptional":true,"token":{"identifier":{"reference":{"__symbol":76,"members":[]}}}},{"isAttribute":false,"isHost":false,"isSelf":false,"isSkipSelf":false,"isOptional":false,"token":{"identifier":{"reference":{"__symbol":66,"members":[]}}}}],"multi":false},"module":{"reference":{"__symbol":79,"members":[]},"diDeps":[],"lifecycleHooks":[]}},{"provider":{"token":{"identifier":{"reference":{"__symbol":78,"members":[]}}},"useClass":null,"useFactory":{"reference":{"__symbol":80,"members":[]},"diDeps":[{"isAttribute":false,"isHost":false,"isSelf":false,"isSkipSelf":false,"isOptional":false,"token":{"identifier":{"reference":{"__symbol":64,"members":[]}}}}]},"deps":[{"isAttribute":false,"isHost":false,"isSelf":false,"isSkipSelf":false,"isOptional":false,"token":{"identifier":{"reference":{"__symbol":64,"members":[]}}}}],"multi":false},"module":{"reference":{"__symbol":79,"members":[]},"diDeps":[],"lifecycleHooks":[]}},{"provider":{"token":{"identifier":{"reference":{"__symbol":81,"members":[]}}},"useClass":null,"useFactory":{"reference":{"__symbol":82,"members":[]},"diDeps":[{"isAttribute":false,"isHost":false,"isSelf":false,"isSkipSelf":true,"isOptional":true,"token":{"identifier":{"reference":{"__symbol":81,"members":[]}}}}]},"deps":[{"isAttribute":false,"isHost":false,"isSelf":false,"isSkipSelf":true,"isOptional":true,"token":{"identifier":{"reference":{"__symbol":81,"members":[]}}}}],"multi":false},"module":{"reference":{"__symbol":83,"members":[]},"diDeps":[],"lifecycleHooks":[]}},{"provider":{"token":{"identifier":{"reference":{"__symbol":84,"members":[]},"diDeps":[],"lifecycleHooks":[]}},"useClass":{"reference":{"__symbol":84,"members":[]},"diDeps":[],"lifecycleHooks":[]},"useFactory":null,"deps":[],"multi":false},"module":{"reference":{"__symbol":85,"members":[]},"diDeps":[],"lifecycleHooks":[]}},{"provider":{"token":{"identifier":{"reference":{"__symbol":86,"members":[]}}},"useClass":null,"useFactory":{"reference":{"__symbol":87,"members":[]},"diDeps":[{"isAttribute":false,"isHost":false,"isSelf":false,"isSkipSelf":false,"isOptional":false,"token":{"identifier":{"reference":{"__symbol":64,"members":[]}}}}]},"deps":[{"isAttribute":false,"isHost":false,"isSelf":false,"isSkipSelf":false,"isOptional":false,"token":{"identifier":{"reference":{"__symbol":64,"members":[]}}}}],"multi":false},"module":{"reference":{"__symbol":88,"members":[]},"diDeps":[],"lifecycleHooks":[]}},{"provider":{"token":{"identifier":{"reference":{"__symbol":89,"members":[]}}},"useClass":null,"useFactory":{"reference":{"__symbol":90,"members":[]},"diDeps":[{"isAttribute":false,"isHost":false,"isSelf":false,"isSkipSelf":false,"isOptional":false,"token":{"identifier":{"reference":{"__symbol":64,"members":[]}}}}]},"deps":[{"isAttribute":false,"isHost":false,"isSelf":false,"isSkipSelf":false,"isOptional":false,"token":{"identifier":{"reference":{"__symbol":64,"members":[]}}}}],"multi":false},"module":{"reference":{"__symbol":91,"members":[]},"diDeps":[],"lifecycleHooks":[]}},{"provider":{"token":{"identifier":{"reference":{"__symbol":92,"members":[]}}},"useClass":{"reference":{"__symbol":93,"members":[]},"diDeps":[{"isAttribute":false,"isHost":false,"isSelf":false,"isSkipSelf":false,"isOptional":true,"token":{"identifier":{"reference":{"__symbol":94,"members":[]}}}},{"isAttribute":false,"isHost":false,"isSelf":false,"isSkipSelf":false,"isOptional":true,"token":{"identifier":{"reference":{"__symbol":95,"members":[]}}}}],"lifecycleHooks":[]},"useFactory":null,"deps":[{"isAttribute":false,"isHost":false,"isSelf":false,"isSkipSelf":false,"isOptional":true,"token":{"identifier":{"reference":{"__symbol":94,"members":[]}}}},{"isAttribute":false,"isHost":false,"isSelf":false,"isSkipSelf":false,"isOptional":true,"token":{"identifier":{"reference":{"__symbol":95,"members":[]}}}}],"multi":false},"module":{"reference":{"__symbol":91,"members":[]},"diDeps":[],"lifecycleHooks":[]}},{"provider":{"token":{"identifier":{"reference":{"__symbol":96,"members":[]}}},"useClass":null,"useFactory":{"reference":{"__symbol":97,"members":[]},"diDeps":[{"isAttribute":false,"isHost":false,"isSelf":false,"isSkipSelf":true,"isOptional":true,"token":{"identifier":{"reference":{"__symbol":96,"members":[]}}}}]},"deps":[{"isAttribute":false,"isHost":false,"isSelf":false,"isSkipSelf":true,"isOptional":true,"token":{"identifier":{"reference":{"__symbol":96,"members":[]}}}}],"multi":false},"module":{"reference":{"__symbol":98,"members":[]},"diDeps":[],"lifecycleHooks":[]}},{"provider":{"token":{"identifier":{"reference":{"__symbol":99,"members":[]},"diDeps":[],"lifecycleHooks":[]}},"useClass":{"reference":{"__symbol":99,"members":[]},"diDeps":[],"lifecycleHooks":[]},"useFactory":null,"deps":[],"multi":false},"module":{"reference":{"__symbol":100,"members":[]},"diDeps":[],"lifecycleHooks":[]}},{"provider":{"token":{"identifier":{"reference":{"__symbol":92,"members":[]}}},"useClass":{"reference":{"__symbol":93,"members":[]},"diDeps":[{"isAttribute":false,"isHost":false,"isSelf":false,"isSkipSelf":false,"isOptional":true,"token":{"identifier":{"reference":{"__symbol":94,"members":[]}}}},{"isAttribute":false,"isHost":false,"isSelf":false,"isSkipSelf":false,"isOptional":true,"token":{"identifier":{"reference":{"__symbol":95,"members":[]}}}}],"lifecycleHooks":[]},"useFactory":null,"deps":[{"isAttribute":false,"isHost":false,"isSelf":false,"isSkipSelf":false,"isOptional":true,"token":{"identifier":{"reference":{"__symbol":94,"members":[]}}}},{"isAttribute":false,"isHost":false,"isSelf":false,"isSkipSelf":false,"isOptional":true,"token":{"identifier":{"reference":{"__symbol":95,"members":[]}}}}],"multi":false},"module":{"reference":{"__symbol":101,"members":[]},"diDeps":[],"lifecycleHooks":[]}},{"provider":{"token":{"identifier":{"reference":{"__symbol":102,"members":[]},"diDeps":[{"isAttribute":false,"isHost":false,"isSelf":false,"isSkipSelf":false,"isOptional":false,"token":{"identifier":{"reference":{"__symbol":67,"members":[]}}}},{"isAttribute":false,"isHost":false,"isSelf":false,"isSkipSelf":false,"isOptional":false,"token":{"identifier":{"reference":{"__symbol":56,"members":[]}}}},{"isAttribute":false,"isHost":false,"isSelf":false,"isSkipSelf":false,"isOptional":false,"token":{"identifier":{"reference":{"__symbol":103,"members":[]}}}},{"isAttribute":false,"isHost":false,"isSelf":false,"isSkipSelf":false,"isOptional":false,"token":{"identifier":{"reference":{"__symbol":104,"members":[]}}}}],"lifecycleHooks":[]}},"useClass":{"reference":{"__symbol":102,"members":[]},"diDeps":[{"isAttribute":false,"isHost":false,"isSelf":false,"isSkipSelf":false,"isOptional":false,"token":{"identifier":{"reference":{"__symbol":67,"members":[]}}}},{"isAttribute":false,"isHost":false,"isSelf":false,"isSkipSelf":false,"isOptional":false,"token":{"identifier":{"reference":{"__symbol":56,"members":[]}}}},{"isAttribute":false,"isHost":false,"isSelf":false,"isSkipSelf":false,"isOptional":false,"token":{"identifier":{"reference":{"__symbol":103,"members":[]}}}},{"isAttribute":false,"isHost":false,"isSelf":false,"isSkipSelf":false,"isOptional":false,"token":{"identifier":{"reference":{"__symbol":104,"members":[]}}}}],"lifecycleHooks":[]},"useFactory":null,"deps":[{"isAttribute":false,"isHost":false,"isSelf":false,"isSkipSelf":false,"isOptional":false,"token":{"identifier":{"reference":{"__symbol":67,"members":[]}}}},{"isAttribute":false,"isHost":false,"isSelf":false,"isSkipSelf":false,"isOptional":false,"token":{"identifier":{"reference":{"__symbol":56,"members":[]}}}},{"isAttribute":false,"isHost":false,"isSelf":false,"isSkipSelf":false,"isOptional":false,"token":{"identifier":{"reference":{"__symbol":103,"members":[]}}}},{"isAttribute":false,"isHost":false,"isSelf":false,"isSkipSelf":false,"isOptional":false,"token":{"identifier":{"reference":{"__symbol":104,"members":[]}}}}],"multi":false},"module":{"reference":{"__symbol":105,"members":[]},"diDeps":[],"lifecycleHooks":[]}},{"provider":{"token":{"identifier":{"reference":{"__symbol":106,"members":[]}}},"useClass":null,"useValue":[{"path":"one-two-three/home","component":{"__symbol":27,"members":[]}},{"path":"one-two-three/particips/list","component":{"__symbol":29,"members":[]}},{"path":"one-two-three/particips/add","component":{"__symbol":31,"members":[]}},{"path":"one-two-three/particips/:participId","component":{"__symbol":31,"members":[]}},{"path":"one-two-three/protocols/:projectTestId","component":{"__symbol":33,"members":[]}},{"path":"one-two-three/protocol/:participTestId","component":{"__symbol":35,"members":[]}},{"path":"one-two-three","redirectTo":"one-two-three/home","pathMatch":"full"}],"useFactory":null,"multi":true},"module":{"reference":{"__symbol":0,"members":[]},"diDeps":[],"lifecycleHooks":[]}},{"provider":{"token":{"identifier":{"reference":{"__symbol":107,"members":[]},"diDeps":[{"isAttribute":false,"isHost":false,"isSelf":false,"isSkipSelf":false,"isOptional":false,"token":{"identifier":{"reference":{"__symbol":52,"members":[]}}}}],"lifecycleHooks":[]}},"useClass":{"reference":{"__symbol":107,"members":[]},"diDeps":[{"isAttribute":false,"isHost":false,"isSelf":false,"isSkipSelf":false,"isOptional":false,"token":{"identifier":{"reference":{"__symbol":52,"members":[]}}}}],"lifecycleHooks":[]},"useFactory":null,"deps":[{"isAttribute":false,"isHost":false,"isSelf":false,"isSkipSelf":false,"isOptional":false,"token":{"identifier":{"reference":{"__symbol":52,"members":[]}}}}],"multi":false},"module":{"reference":{"__symbol":0,"members":[]},"diDeps":[],"lifecycleHooks":[]}},{"provider":{"token":{"identifier":{"reference":{"__symbol":108,"members":[]},"diDeps":[{"isAttribute":false,"isHost":false,"isSelf":false,"isSkipSelf":false,"isOptional":false,"token":{"identifier":{"reference":{"__symbol":52,"members":[]}}}}],"lifecycleHooks":[]}},"useClass":{"reference":{"__symbol":108,"members":[]},"diDeps":[{"isAttribute":false,"isHost":false,"isSelf":false,"isSkipSelf":false,"isOptional":false,"token":{"identifier":{"reference":{"__symbol":52,"members":[]}}}}],"lifecycleHooks":[]},"useFactory":null,"deps":[{"isAttribute":false,"isHost":false,"isSelf":false,"isSkipSelf":false,"isOptional":false,"token":{"identifier":{"reference":{"__symbol":52,"members":[]}}}}],"multi":false},"module":{"reference":{"__symbol":0,"members":[]},"diDeps":[],"lifecycleHooks":[]}}],"modules":[{"reference":{"__symbol":41,"members":[]},"diDeps":[],"lifecycleHooks":[]},{"reference":{"__symbol":45,"members":[]},"diDeps":[],"lifecycleHooks":[]},{"reference":{"__symbol":51,"members":[]},"diDeps":[],"lifecycleHooks":[]},{"reference":{"__symbol":109,"members":[]},"diDeps":[],"lifecycleHooks":[]},{"reference":{"__symbol":61,"members":[]},"diDeps":[],"lifecycleHooks":[]},{"reference":{"__symbol":63,"members":[]},"diDeps":[],"lifecycleHooks":[]},{"reference":{"__symbol":110,"members":[]},"diDeps":[],"lifecycleHooks":[]},{"reference":{"__symbol":95,"members":[]},"diDeps":[{"isAttribute":false,"isHost":false,"isSelf":false,"isSkipSelf":false,"isOptional":true,"token":{"identifier":{"reference":{"__symbol":111,"members":[]}}}},{"isAttribute":false,"isHost":false,"isSelf":false,"isSkipSelf":false,"isOptional":true,"token":{"identifier":{"reference":{"__symbol":112,"members":[]}}}}],"lifecycleHooks":[]},{"reference":{"__symbol":113,"members":[]},"diDeps":[],"lifecycleHooks":[]},{"reference":{"__symbol":114,"members":[]},"diDeps":[],"lifecycleHooks":[]},{"reference":{"__symbol":115,"members":[]},"diDeps":[],"lifecycleHooks":[]},{"reference":{"__symbol":116,"members":[]},"diDeps":[],"lifecycleHooks":[]},{"reference":{"__symbol":117,"members":[]},"diDeps":[],"lifecycleHooks":[]},{"reference":{"__symbol":73,"members":[]},"diDeps":[],"lifecycleHooks":[]},{"reference":{"__symbol":79,"members":[]},"diDeps":[],"lifecycleHooks":[]},{"reference":{"__symbol":118,"members":[]},"diDeps":[],"lifecycleHooks":[]},{"reference":{"__symbol":119,"members":[]},"diDeps":[],"lifecycleHooks":[]},{"reference":{"__symbol":120,"members":[]},"diDeps":[],"lifecycleHooks":[]},{"reference":{"__symbol":83,"members":[]},"diDeps":[],"lifecycleHooks":[]},{"reference":{"__symbol":121,"members":[]},"diDeps":[],"lifecycleHooks":[]},{"reference":{"__symbol":122,"members":[]},"diDeps":[],"lifecycleHooks":[]},{"reference":{"__symbol":85,"members":[]},"diDeps":[],"lifecycleHooks":[]},{"reference":{"__symbol":123,"members":[]},"diDeps":[],"lifecycleHooks":[]},{"reference":{"__symbol":88,"members":[]},"diDeps":[],"lifecycleHooks":[]},{"reference":{"__symbol":124,"members":[]},"diDeps":[],"lifecycleHooks":[]},{"reference":{"__symbol":91,"members":[]},"diDeps":[],"lifecycleHooks":[]},{"reference":{"__symbol":98,"members":[]},"diDeps":[],"lifecycleHooks":[]},{"reference":{"__symbol":125,"members":[]},"diDeps":[],"lifecycleHooks":[]},{"reference":{"__symbol":126,"members":[]},"diDeps":[],"lifecycleHooks":[]},{"reference":{"__symbol":100,"members":[]},"diDeps":[],"lifecycleHooks":[]},{"reference":{"__symbol":127,"members":[]},"diDeps":[],"lifecycleHooks":[]},{"reference":{"__symbol":128,"members":[]},"diDeps":[],"lifecycleHooks":[]},{"reference":{"__symbol":129,"members":[]},"diDeps":[],"lifecycleHooks":[]},{"reference":{"__symbol":101,"members":[]},"diDeps":[],"lifecycleHooks":[]},{"reference":{"__symbol":130,"members":[]},"diDeps":[],"lifecycleHooks":[]},{"reference":{"__symbol":131,"members":[]},"diDeps":[],"lifecycleHooks":[]},{"reference":{"__symbol":132,"members":[]},"diDeps":[],"lifecycleHooks":[]},{"reference":{"__symbol":133,"members":[]},"diDeps":[],"lifecycleHooks":[]},{"reference":{"__symbol":134,"members":[]},"diDeps":[],"lifecycleHooks":[]},{"reference":{"__symbol":135,"members":[]},"diDeps":[],"lifecycleHooks":[]},{"reference":{"__symbol":136,"members":[]},"diDeps":[],"lifecycleHooks":[]},{"reference":{"__symbol":137,"members":[]},"diDeps":[],"lifecycleHooks":[]},{"reference":{"__symbol":138,"members":[]},"diDeps":[],"lifecycleHooks":[]},{"reference":{"__symbol":139,"members":[]},"diDeps":[],"lifecycleHooks":[]},{"reference":{"__symbol":140,"members":[]},"diDeps":[],"lifecycleHooks":[]},{"reference":{"__symbol":141,"members":[]},"diDeps":[],"lifecycleHooks":[]},{"reference":{"__symbol":142,"members":[]},"diDeps":[],"lifecycleHooks":[]},{"reference":{"__symbol":143,"members":[]},"diDeps":[],"lifecycleHooks":[]},{"reference":{"__symbol":144,"members":[]},"diDeps":[],"lifecycleHooks":[]},{"reference":{"__symbol":145,"members":[]},"diDeps":[],"lifecycleHooks":[]},{"reference":{"__symbol":146,"members":[]},"diDeps":[],"lifecycleHooks":[]},{"reference":{"__symbol":105,"members":[]},"diDeps":[],"lifecycleHooks":[]},{"reference":{"__symbol":147,"members":[]},"diDeps":[],"lifecycleHooks":[]},{"reference":{"__symbol":148,"members":[]},"diDeps":[],"lifecycleHooks":[]},{"reference":{"__symbol":149,"members":[]},"diDeps":[],"lifecycleHooks":[]},{"reference":{"__symbol":150,"members":[]},"diDeps":[],"lifecycleHooks":[]},{"reference":{"__symbol":151,"members":[]},"diDeps":[],"lifecycleHooks":[]},{"reference":{"__symbol":152,"members":[]},"diDeps":[],"lifecycleHooks":[]},{"reference":{"__symbol":153,"members":[]},"diDeps":[],"lifecycleHooks":[]},{"reference":{"__symbol":154,"members":[]},"diDeps":[],"lifecycleHooks":[]},{"reference":{"__symbol":155,"members":[]},"diDeps":[],"lifecycleHooks":[]},{"reference":{"__symbol":156,"members":[]},"diDeps":[{"isAttribute":false,"isHost":false,"isSelf":false,"isSkipSelf":false,"isOptional":true,"token":{"identifier":{"reference":{"__symbol":157,"members":[]}}}},{"isAttribute":false,"isHost":false,"isSelf":false,"isSkipSelf":false,"isOptional":true,"token":{"identifier":{"reference":{"__symbol":158,"members":[]}}}}],"lifecycleHooks":[]},{"reference":{"__symbol":0,"members":[]},"diDeps":[],"lifecycleHooks":[]}],"exportedDirectives":[{"reference":{"__symbol":159,"members":[]}},{"reference":{"__symbol":160,"members":[]}},{"reference":{"__symbol":161,"members":[]}},{"reference":{"__symbol":162,"members":[]}},{"reference":{"__symbol":25,"members":[]}}],"exportedPipes":[]}}],"symbols":[{"__symbol":0,"name":"OneTwoThreeModule","filePath":"./one-two-three.module"},{"__symbol":1,"name":"MatDialogContainer","filePath":"@angular/material/dialog/typings/index"},{"__symbol":2,"name":"MatDialogContainerNgFactory","filePath":"../../node_modules/@angular/material/dialog/typings/index.ngfactory"},{"__symbol":3,"name":"TooltipComponent","filePath":"@angular/material/tooltip/typings/index"},{"__symbol":4,"name":"TooltipComponentNgFactory","filePath":"../../node_modules/@angular/material/tooltip/typings/index.ngfactory"},{"__symbol":5,"name":"MatSnackBarContainer","filePath":"@angular/material/snack-bar/typings/index"},{"__symbol":6,"name":"MatSnackBarContainerNgFactory","filePath":"../../node_modules/@angular/material/snack-bar/typings/index.ngfactory"},{"__symbol":7,"name":"SimpleSnackBar","filePath":"@angular/material/snack-bar/typings/index"},{"__symbol":8,"name":"SimpleSnackBarNgFactory","filePath":"../../node_modules/@angular/material/snack-bar/typings/index.ngfactory"},{"__symbol":9,"name":"ConfirmDialogComponent","filePath":"../shared/confirm-dialog/confirm-dialog.component"},{"__symbol":10,"name":"ConfirmDialogComponentNgFactory","filePath":"../shared/confirm-dialog/confirm-dialog.component.ngfactory"},{"__symbol":11,"name":"NgbAlert","filePath":"@ng-bootstrap/ng-bootstrap"},{"__symbol":12,"name":"NgbAlertNgFactory","filePath":"../../node_modules/@ng-bootstrap/ng-bootstrap/ng-bootstrap.ngfactory"},{"__symbol":13,"name":"NgbDatepicker","filePath":"@ng-bootstrap/ng-bootstrap"},{"__symbol":14,"name":"NgbDatepickerNgFactory","filePath":"../../node_modules/@ng-bootstrap/ng-bootstrap/ng-bootstrap.ngfactory"},{"__symbol":15,"name":"ɵu","filePath":"@ng-bootstrap/ng-bootstrap"},{"__symbol":16,"name":"ɵuNgFactory","filePath":"../../node_modules/@ng-bootstrap/ng-bootstrap/ng-bootstrap.ngfactory"},{"__symbol":17,"name":"ɵv","filePath":"@ng-bootstrap/ng-bootstrap"},{"__symbol":18,"name":"ɵvNgFactory","filePath":"../../node_modules/@ng-bootstrap/ng-bootstrap/ng-bootstrap.ngfactory"},{"__symbol":19,"name":"ɵn","filePath":"@ng-bootstrap/ng-bootstrap"},{"__symbol":20,"name":"ɵnNgFactory","filePath":"../../node_modules/@ng-bootstrap/ng-bootstrap/ng-bootstrap.ngfactory"},{"__symbol":21,"name":"ɵq","filePath":"@ng-bootstrap/ng-bootstrap"},{"__symbol":22,"name":"ɵqNgFactory","filePath":"../../node_modules/@ng-bootstrap/ng-bootstrap/ng-bootstrap.ngfactory"},{"__symbol":23,"name":"ɵr","filePath":"@ng-bootstrap/ng-bootstrap"},{"__symbol":24,"name":"ɵrNgFactory","filePath":"../../node_modules/@ng-bootstrap/ng-bootstrap/ng-bootstrap.ngfactory"},{"__symbol":25,"name":"ɵEmptyOutletComponent","filePath":"@angular/router"},{"__symbol":26,"name":"ɵEmptyOutletComponentNgFactory","filePath":"../../node_modules/@angular/router/router.ngfactory"},{"__symbol":27,"name":"HomeComponent","filePath":"./home/home.component"},{"__symbol":28,"name":"HomeComponentNgFactory","filePath":"./home/home.component.ngfactory"},{"__symbol":29,"name":"ParticipsListComponent","filePath":"./particips/list/particips-list.component"},{"__symbol":30,"name":"ParticipsListComponentNgFactory","filePath":"./particips/list/particips-list.component.ngfactory"},{"__symbol":31,"name":"AddOrUpdateComponent","filePath":"./particips/add-or-update/add-or-update.component"},{"__symbol":32,"name":"AddOrUpdateComponentNgFactory","filePath":"./particips/add-or-update/add-or-update.component.ngfactory"},{"__symbol":33,"name":"ProtocolsListComponent","filePath":"./question-protocols/list/protocols-list.component"},{"__symbol":34,"name":"ProtocolsListComponentNgFactory","filePath":"./question-protocols/list/protocols-list.component.ngfactory"},{"__symbol":35,"name":"ProtocolComponent","filePath":"./question-protocols/protocol/protocol.component"},{"__symbol":36,"name":"ProtocolComponentNgFactory","filePath":"./question-protocols/protocol/protocol.component.ngfactory"},{"__symbol":37,"name":"NgLocalization","filePath":"@angular/common"},{"__symbol":38,"name":"NgLocaleLocalization","filePath":"@angular/common"},{"__symbol":39,"name":"LOCALE_ID","filePath":"@angular/core"},{"__symbol":40,"name":"ɵangular_packages_common_common_a","filePath":"@angular/common"},{"__symbol":41,"name":"CommonModule","filePath":"@angular/common"},{"__symbol":42,"name":"ɵangular_packages_common_http_http_h","filePath":"@angular/common/http/http"},{"__symbol":43,"name":"HttpXsrfTokenExtractor","filePath":"@angular/common/http/http"},{"__symbol":44,"name":"ɵangular_packages_common_http_http_f","filePath":"@angular/common/http/http"},{"__symbol":45,"name":"HttpClientXsrfModule","filePath":"@angular/common/http/http"},{"__symbol":46,"name":"HTTP_INTERCEPTORS","filePath":"@angular/common/http/http"},{"__symbol":47,"name":"ɵangular_packages_common_http_http_g","filePath":"@angular/common/http/http"},{"__symbol":48,"name":"DOCUMENT","filePath":"@angular/common"},{"__symbol":49,"name":"PLATFORM_ID","filePath":"@angular/core"},{"__symbol":50,"name":"ɵangular_packages_common_http_http_e","filePath":"@angular/common/http/http"},{"__symbol":51,"name":"HttpClientModule","filePath":"@angular/common/http/http"},{"__symbol":52,"name":"HttpClient","filePath":"@angular/common/http/http"},{"__symbol":53,"name":"HttpHandler","filePath":"@angular/common/http/http"},{"__symbol":54,"name":"ɵHttpInterceptingHandler","filePath":"@angular/common/http/http"},{"__symbol":55,"name":"HttpBackend","filePath":"@angular/common/http/http"},{"__symbol":56,"name":"Injector","filePath":"@angular/core"},{"__symbol":57,"name":"HttpXhrBackend","filePath":"@angular/common/http/http"},{"__symbol":58,"name":"XhrFactory","filePath":"@angular/common/http/http"},{"__symbol":59,"name":"ɵangular_packages_common_http_http_d","filePath":"@angular/common/http/http"},{"__symbol":60,"name":"ɵangular_packages_forms_forms_j","filePath":"@angular/forms"},{"__symbol":61,"name":"FormsModule","filePath":"@angular/forms"},{"__symbol":62,"name":"FormBuilder","filePath":"@angular/forms"},{"__symbol":63,"name":"ReactiveFormsModule","filePath":"@angular/forms"},{"__symbol":64,"name":"Overlay","filePath":"@angular/cdk/overlay/typings/index"},{"__symbol":65,"name":"ScrollStrategyOptions","filePath":"@angular/cdk/overlay/typings/index"},{"__symbol":66,"name":"OverlayContainer","filePath":"@angular/cdk/overlay/typings/index"},{"__symbol":67,"name":"ComponentFactoryResolver","filePath":"@angular/core"},{"__symbol":68,"name":"OverlayPositionBuilder","filePath":"@angular/cdk/overlay/typings/index"},{"__symbol":69,"name":"OverlayKeyboardDispatcher","filePath":"@angular/cdk/overlay/typings/index"},{"__symbol":70,"name":"NgZone","filePath":"@angular/core"},{"__symbol":71,"name":"Directionality","filePath":"@angular/cdk/bidi/typings/index"},{"__symbol":72,"name":"Location","filePath":"@angular/common"},{"__symbol":73,"name":"OverlayModule","filePath":"@angular/cdk/overlay/typings/index"},{"__symbol":74,"name":"ɵc","filePath":"@angular/cdk/overlay/typings/index"},{"__symbol":75,"name":"ɵd","filePath":"@angular/cdk/overlay/typings/index"},{"__symbol":76,"name":"MatDialog","filePath":"@angular/material/dialog/typings/index"},{"__symbol":77,"name":"MAT_DIALOG_DEFAULT_OPTIONS","filePath":"@angular/material/dialog/typings/index"},{"__symbol":78,"name":"MAT_DIALOG_SCROLL_STRATEGY","filePath":"@angular/material/dialog/typings/index"},{"__symbol":79,"name":"MatDialogModule","filePath":"@angular/material/dialog/typings/index"},{"__symbol":80,"name":"MAT_DIALOG_SCROLL_STRATEGY_PROVIDER_FACTORY","filePath":"@angular/material/dialog/typings/index"},{"__symbol":81,"name":"MatSortHeaderIntl","filePath":"@angular/material/sort/typings/index"},{"__symbol":82,"name":"MAT_SORT_HEADER_INTL_PROVIDER_FACTORY","filePath":"@angular/material/sort/typings/index"},{"__symbol":83,"name":"MatSortModule","filePath":"@angular/material/sort/typings/index"},{"__symbol":84,"name":"MutationObserverFactory","filePath":"@angular/cdk/observers/typings/index"},{"__symbol":85,"name":"ObserversModule","filePath":"@angular/cdk/observers/typings/index"},{"__symbol":86,"name":"MAT_SELECT_SCROLL_STRATEGY","filePath":"@angular/material/select/typings/index"},{"__symbol":87,"name":"MAT_SELECT_SCROLL_STRATEGY_PROVIDER_FACTORY","filePath":"@angular/material/select/typings/index"},{"__symbol":88,"name":"MatSelectModule","filePath":"@angular/material/select/typings/index"},{"__symbol":89,"name":"MAT_TOOLTIP_SCROLL_STRATEGY","filePath":"@angular/material/tooltip/typings/index"},{"__symbol":90,"name":"MAT_TOOLTIP_SCROLL_STRATEGY_FACTORY","filePath":"@angular/material/tooltip/typings/index"},{"__symbol":91,"name":"MatTooltipModule","filePath":"@angular/material/tooltip/typings/index"},{"__symbol":92,"name":"HAMMER_GESTURE_CONFIG","filePath":"@angular/platform-browser"},{"__symbol":93,"name":"GestureConfig","filePath":"@angular/material/core/typings/index"},{"__symbol":94,"name":"MAT_HAMMER_OPTIONS","filePath":"@angular/material/core/typings/index"},{"__symbol":95,"name":"MatCommonModule","filePath":"@angular/material/core/typings/index"},{"__symbol":96,"name":"MatPaginatorIntl","filePath":"@angular/material/paginator/typings/index"},{"__symbol":97,"name":"MAT_PAGINATOR_INTL_PROVIDER_FACTORY","filePath":"@angular/material/paginator/typings/index"},{"__symbol":98,"name":"MatPaginatorModule","filePath":"@angular/material/paginator/typings/index"},{"__symbol":99,"name":"ErrorStateMatcher","filePath":"@angular/material/core/typings/index"},{"__symbol":100,"name":"MatInputModule","filePath":"@angular/material/input/typings/index"},{"__symbol":101,"name":"MatSlideToggleModule","filePath":"@angular/material/slide-toggle/typings/index"},{"__symbol":102,"name":"NgbModal","filePath":"@ng-bootstrap/ng-bootstrap"},{"__symbol":103,"name":"ɵw","filePath":"@ng-bootstrap/ng-bootstrap"},{"__symbol":104,"name":"NgbModalConfig","filePath":"@ng-bootstrap/ng-bootstrap"},{"__symbol":105,"name":"NgbModalModule","filePath":"@ng-bootstrap/ng-bootstrap"},{"__symbol":106,"name":"ROUTES","filePath":"@angular/router"},{"__symbol":107,"name":"ParticipService","filePath":"../services/one-two-three/particips.service"},{"__symbol":108,"name":"QuestionProtocolService","filePath":"../services/one-two-three/question-protocols.service"},{"__symbol":109,"name":"ɵangular_packages_forms_forms_bc","filePath":"@angular/forms"},{"__symbol":110,"name":"BidiModule","filePath":"@angular/cdk/bidi/typings/index"},{"__symbol":111,"name":"MATERIAL_SANITY_CHECKS","filePath":"@angular/material/core/typings/index"},{"__symbol":112,"name":"HAMMER_LOADER","filePath":"@angular/platform-browser"},{"__symbol":113,"name":"PlatformModule","filePath":"@angular/cdk/platform/typings/index"},{"__symbol":114,"name":"MatRippleModule","filePath":"@angular/material/core/typings/index"},{"__symbol":115,"name":"MatButtonModule","filePath":"@angular/material/button/typings/index"},{"__symbol":116,"name":"PortalModule","filePath":"@angular/cdk/portal/typings/index"},{"__symbol":117,"name":"ScrollingModule","filePath":"@angular/cdk/scrolling/typings/index"},{"__symbol":118,"name":"MatCardModule","filePath":"@angular/material/card/typings/index"},{"__symbol":119,"name":"CdkTableModule","filePath":"@angular/cdk/table/typings/index"},{"__symbol":120,"name":"MatTableModule","filePath":"@angular/material/table/typings/index"},{"__symbol":121,"name":"MatPseudoCheckboxModule","filePath":"@angular/material/core/typings/index"},{"__symbol":122,"name":"MatOptionModule","filePath":"@angular/material/core/typings/index"},{"__symbol":123,"name":"MatFormFieldModule","filePath":"@angular/material/form-field/typings/index"},{"__symbol":124,"name":"A11yModule","filePath":"@angular/cdk/a11y/typings/index"},{"__symbol":125,"name":"MatProgressSpinnerModule","filePath":"@angular/material/progress-spinner/typings/index"},{"__symbol":126,"name":"TextFieldModule","filePath":"@angular/cdk/text-field/typings/index"},{"__symbol":127,"name":"MatToolbarModule","filePath":"@angular/material/toolbar/typings/index"},{"__symbol":128,"name":"MatProgressBarModule","filePath":"@angular/material/progress-bar/typings/index"},{"__symbol":129,"name":"MatSnackBarModule","filePath":"@angular/material/snack-bar/typings/index"},{"__symbol":130,"name":"MatCheckboxModule","filePath":"@angular/material/checkbox/typings/index"},{"__symbol":131,"name":"MatIconModule","filePath":"@angular/material/icon/typings/index"},{"__symbol":132,"name":"MatRadioModule","filePath":"@angular/material/radio/typings/index"},{"__symbol":133,"name":"CdkAccordionModule","filePath":"@angular/cdk/accordion/typings/index"},{"__symbol":134,"name":"MatExpansionModule","filePath":"@angular/material/expansion/typings/index"},{"__symbol":135,"name":"MatLineModule","filePath":"@angular/material/core/typings/index"},{"__symbol":136,"name":"MatDividerModule","filePath":"@angular/material/divider/typings/index"},{"__symbol":137,"name":"MatListModule","filePath":"@angular/material/list/typings/index"},{"__symbol":138,"name":"MaterialModule","filePath":"../material.module"},{"__symbol":139,"name":"SharedModule","filePath":"../shared/shared-module"},{"__symbol":140,"name":"NgbAccordionModule","filePath":"@ng-bootstrap/ng-bootstrap"},{"__symbol":141,"name":"NgbAlertModule","filePath":"@ng-bootstrap/ng-bootstrap"},{"__symbol":142,"name":"NgbButtonsModule","filePath":"@ng-bootstrap/ng-bootstrap"},{"__symbol":143,"name":"NgbCarouselModule","filePath":"@ng-bootstrap/ng-bootstrap"},{"__symbol":144,"name":"NgbCollapseModule","filePath":"@ng-bootstrap/ng-bootstrap"},{"__symbol":145,"name":"NgbDatepickerModule","filePath":"@ng-bootstrap/ng-bootstrap"},{"__symbol":146,"name":"NgbDropdownModule","filePath":"@ng-bootstrap/ng-bootstrap"},{"__symbol":147,"name":"NgbPaginationModule","filePath":"@ng-bootstrap/ng-bootstrap"},{"__symbol":148,"name":"NgbPopoverModule","filePath":"@ng-bootstrap/ng-bootstrap"},{"__symbol":149,"name":"NgbProgressbarModule","filePath":"@ng-bootstrap/ng-bootstrap"},{"__symbol":150,"name":"NgbRatingModule","filePath":"@ng-bootstrap/ng-bootstrap"},{"__symbol":151,"name":"NgbTabsetModule","filePath":"@ng-bootstrap/ng-bootstrap"},{"__symbol":152,"name":"NgbTimepickerModule","filePath":"@ng-bootstrap/ng-bootstrap"},{"__symbol":153,"name":"NgbTooltipModule","filePath":"@ng-bootstrap/ng-bootstrap"},{"__symbol":154,"name":"NgbTypeaheadModule","filePath":"@ng-bootstrap/ng-bootstrap"},{"__symbol":155,"name":"NgbModule","filePath":"@ng-bootstrap/ng-bootstrap"},{"__symbol":156,"name":"RouterModule","filePath":"@angular/router"},{"__symbol":157,"name":"ɵangular_packages_router_router_a","filePath":"@angular/router"},{"__symbol":158,"name":"Router","filePath":"@angular/router"},{"__symbol":159,"name":"RouterOutlet","filePath":"@angular/router"},{"__symbol":160,"name":"RouterLink","filePath":"@angular/router"},{"__symbol":161,"name":"RouterLinkWithHref","filePath":"@angular/router"},{"__symbol":162,"name":"RouterLinkActive","filePath":"@angular/router"}]}